aiopayok/__init__.py
aiopayok/api.py
aiopayok/base.py
aiopayok/const.py
aiopayok/exceptions/__init__.py
aiopayok/exceptions/factory.py
aiopayok/models/balance.py
aiopayok/models/transaction.py
aiopayok-0.2.0.dist-info/LICENSE
aiopayok-0.2.0.dist-info/WHEEL
aiopayok-0.2.0.dist-info/METADATA
aiopayok-0.2.0.dist-info/RECORD
