Metadata-Version: 2.1
Name: aiopayok
Version: 0.2.0
Summary: payok.io asynchronous python wrapper
Home-page: https://github.com/layerqa/aiopayok
License: GPL-3.0-only
Keywords: payok,aiopayok,payok api
Author: layerqa
Requires-Python: >=3.8,<4.0
Classifier: License :: OSI Approved :: GNU General Public License v3 (GPLv3)
Classifier: Programming Language :: Python :: 3
Classifier: Programming Language :: Python :: 3.10
Classifier: Programming Language :: Python :: 3.8
Classifier: Programming Language :: Python :: 3.9
Requires-Dist: aiohttp (>=3.8.1,<4.0.0)
Requires-Dist: certifi (>=2022.5.18,<2023.0.0)
Requires-Dist: pydantic (>=1.9.1,<2.0.0)
Project-URL: Documentation, https://payok.io/cabinet/documentation/doc_main.php
Project-URL: Repository, https://github.com/layerqa/aiopayok
